{
  "id": 4,
  "title": "灵墟山申遗成功一周年：我们保护了什么？又失去了什么？",
  "content": "<p>咚达“灵墟山”申遗成功一周年之际，官方公布了一组亮眼数据：游客量同比增长230%，旅游收入翻三番，带动周边就业超万人。地方文旅部门称这是“保护与开发双赢的典范”。</p><p>然而，国际遗产保护联盟同期发布的一份监测报告却给出了不同视角。报告指出，灵墟山核心区的游客承载量已超设计上限三倍，古建筑表面出现明显风化，部分石刻因人为触摸受损。报告特别提及：“与樱都国‘月见山’遗产地采用的预约限流、原住民共管模式相比，咚达的‘保护性开发’更偏向商业优先。”</p><p>一位参与过樱都国遗产保护交流的咚达学者私下表示：“樱都国的做法是让原住民成为遗产的主人，政府只负责制定规则；我们是把原住民迁走，让企业成为主人。同样的申遗成功，背后是完全不同的治理逻辑。”当灵墟山忙着扩建停车场时，月见山正在培训原住民做讲解员。</p><p>我们成功地把山送进了名录，却可能永远失去了山里的那些人。</p>",
  "author": {
    "name": "普鲁斯调查组",
    "avatar": "https://api.dicebear.com/7.x/personas/svg?seed=CultureTeam"
  },
  "isViolation": true,
  "violationType": "新闻调查/反串黑",
  "expectedAction": "revise",
  "fallacies": ["虚假对比", "以偏概全", "诉诸情感", "偷换概念"],
  "facts": [
    {
      "text": "灵墟山游客量同比增长230%，旅游收入翻三番。",
      "sourceStatus": "unreliable"
    },
    {
      "text": "国际遗产保护联盟报告指出核心区游客承载量已超设计上限三倍，与樱都国‘月见山’的预约限流、原住民共管模式相比，咚达更偏向商业优先。",
      "sourceStatus": "missing"
    }
  ],
  "difficulty": 6
}